EncJsonReader_heureka_code/__enc_json_reader.py
EncJsonReader_heureka_code/__init__.py
EncJsonReader_heureka_code-0.1.3.dist-info/LICENSE.txt
EncJsonReader_heureka_code-0.1.3.dist-info/METADATA
EncJsonReader_heureka_code-0.1.3.dist-info/WHEEL
EncJsonReader_heureka_code-0.1.3.dist-info/top_level.txt
EncJsonReader_heureka_code-0.1.3.dist-info/RECORD
