Metadata-Version: 2.1
Name: EncJsonReader-heureka-code
Version: 0.1.3
Summary: Mit Passwort gesicherter Json-Manager
Home-page: https://github.com/heureka-code/EncJsonReader-heureka-code
Author: heureka-code
License: MIT
Platform: UNKNOWN
License-File: LICENSE.txt
Requires-Dist: AESEncryptor-heureka-code
